torch_scatter/__init__.py
torch_scatter/placeholder.py
torch_scatter/scatter.py
torch_scatter/segment_coo.py
torch_scatter/segment_csr.py
torch_scatter/testing.py
torch_scatter/utils.py
torch_scatter/composite/__init__.py
torch_scatter/composite/logsumexp.py
torch_scatter/composite/softmax.py
torch_scatter/composite/std.py
torch_scatter_carate-2.1.1.dist-info/LICENSE
torch_scatter_carate-2.1.1.dist-info/METADATA
torch_scatter_carate-2.1.1.dist-info/WHEEL
torch_scatter_carate-2.1.1.dist-info/top_level.txt
torch_scatter_carate-2.1.1.dist-info/RECORD
