Metadata-Version: 2.1
Name: torch-scatter-carate
Version: 2.1.1
Summary: PyTorch Extension Library of Optimized Scatter Operations adapted for compatibility
Home-page: https://github.com/rusty1s/pytorch_scatter
Download-URL: https://github.com/rusty1s/pytorch_scatter/archive/2.1.1.tar.gz
Author: Matthias Fey
Author-email: julian.kleber@sail.black
Keywords: pytorch,scatter,segment,gather
Classifier: Development Status :: 5 - Production/Stable
Classifier: License :: OSI Approved :: MIT License
Classifier: Programming Language :: Python
Classifier: Programming Language :: Python :: 3.7
Classifier: Programming Language :: Python :: 3.8
Classifier: Programming Language :: Python :: 3.9
Classifier: Programming Language :: Python :: 3.10
Classifier: Programming Language :: Python :: 3 :: Only
Requires-Python: >=3.7
License-File: LICENSE
Requires-Dist: torch
Provides-Extra: test
Requires-Dist: pytest ; extra == 'test'
Requires-Dist: pytest-cov ; extra == 'test'
